spoef/__init__.py
spoef/feature_generation.py
spoef/transforms.py
spoef/utils.py
SPOEF-0.0.3.dist-info/LICENSE
SPOEF-0.0.3.dist-info/METADATA
SPOEF-0.0.3.dist-info/WHEEL
SPOEF-0.0.3.dist-info/top_level.txt
SPOEF-0.0.3.dist-info/RECORD
